{
  "_comment": "应世类型覆盖台账。一类苦参一次, 防重、保全覆盖。",
  "covered": {
    "父母教育焦虑": {
      "koan": "k003",
      "concept": "我执",
      "at": "2026-06-20T14:44:21Z",
      "q_count": 67
    },
    "子女教育焦虑": {
      "koan": "k004",
      "concept": "我执",
      "at": "2026-06-20T16:10:18Z",
      "q_count": 51
    },
    "养老困境": {
      "koan": "k005",
      "concept": "慈悲",
      "at": "2026-06-20T17:18:28Z",
      "q_count": 45
    },
    "代际价值观冲突": {
      "koan": "k006",
      "concept": "我执",
      "at": "2026-06-20T18:10:26Z",
      "q_count": 42
    },
    "生活成本压力": {
      "koan": "k007",
      "concept": "厌离",
      "at": "2026-06-20T18:50:17Z",
      "q_count": 40
    },
    "教育焦虑": {
      "koan": "k003",
      "concept": "(折叠近义)",
      "at": "2026-06-20T19:50:06Z",
      "q_count": 33
    },
    "外貌焦虑": {
      "koan": "k008",
      "concept": "空",
      "at": "2026-06-20T19:50:27Z",
      "q_count": 31
    },
    "职业发展焦虑": {
      "koan": "k009",
      "concept": "解脱",
      "at": "2026-06-20T20:00:21Z",
      "q_count": 31
    },
    "求职焦虑": {
      "koan": "k009",
      "concept": "(折叠近义)",
      "at": "2026-06-20T20:50:06Z",
      "q_count": 31
    },
    "职场压力": {
      "koan": "k010",
      "concept": "我执",
      "at": "2026-06-20T20:50:29Z",
      "q_count": 30
    },
    "文化认同困惑": {
      "koan": "k011",
      "concept": "我执",
      "at": "2026-06-20T21:30:17Z",
      "q_count": 29
    },
    "婚恋压力": {
      "koan": "k012",
      "concept": "爱欲",
      "at": "2026-06-20T22:10:24Z",
      "q_count": 28
    },
    "职场变动": {
      "koan": "k013",
      "concept": "我执",
      "at": "2026-06-20T22:40:15Z",
      "q_count": 28
    },
    "婚嫁习俗困扰": {
      "koan": "k014",
      "concept": "情债",
      "at": "2026-06-20T23:20:26Z",
      "q_count": 26
    },
    "亲子教育观念冲突": {
      "koan": "k015",
      "concept": "师位之疑",
      "at": "2026-06-20T23:30:20Z",
      "q_count": 26
    },
    "身体形象焦虑": {
      "koan": "k008",
      "concept": "(折叠近义)",
      "at": "2026-06-20T23:40:06Z",
      "q_count": 26
    },
    "代际观念冲突": {
      "koan": "k006",
      "concept": "(折叠近义)",
      "at": "2026-06-20T23:40:13Z",
      "q_count": 25
    },
    "生活便利带来的困惑": {
      "koan": "k016",
      "concept": "依赖",
      "at": "2026-06-20T23:40:44Z",
      "q_count": 25
    },
    "职场困境": {
      "koan": "k017",
      "concept": "割裂身份",
      "at": "2026-06-21T00:00:37Z",
      "q_count": 24
    },
    "心理健康困扰": {
      "koan": "k018",
      "concept": "依赖",
      "at": "2026-06-21T00:10:22Z",
      "q_count": 24
    },
    "身体焦虑": {
      "koan": "k008",
      "concept": "(折叠近义)",
      "at": "2026-06-21T00:20:06Z",
      "q_count": 23
    },
    "避免受骗": {
      "koan": "k019",
      "concept": "自欺",
      "at": "2026-06-21T00:20:33Z",
      "q_count": 21
    },
    "分手危机": {
      "koan": "k020",
      "concept": "平价自我",
      "at": "2026-06-21T00:30:20Z",
      "q_count": 21
    },
    "子女教育压力": {
      "koan": "k004",
      "concept": "(折叠近义)",
      "at": "2026-06-21T00:40:06Z",
      "q_count": 21
    },
    "生活富裕后的迷失": {
      "koan": "k021",
      "concept": "内在尊严",
      "at": "2026-06-21T00:40:24Z",
      "q_count": 21
    },
    "修行疑惑": {
      "koan": "k022",
      "concept": "戒慈之隙",
      "at": "2026-06-21T00:50:18Z",
      "q_count": 20
    },
    "人际冲突": {
      "koan": "k023",
      "concept": "执对",
      "at": "2026-06-21T10:01:05Z",
      "q_count": 20
    },
    "消化不良": {
      "koan": "k024",
      "concept": "忧结",
      "at": "2026-06-21T11:10:32Z",
      "q_count": 20
    },
    "癌症预防": {
      "koan": "k025",
      "concept": "食畏",
      "at": "2026-06-21T11:50:31Z",
      "q_count": 20
    },
    "社会偏见": {
      "koan": "k026",
      "concept": "教中之愧",
      "at": "2026-06-21T12:50:37Z",
      "q_count": 20
    },
    "职业倦怠": {
      "koan": "k027",
      "concept": "零件之觉",
      "at": "2026-06-21T14:10:35Z",
      "q_count": 20
    },
    "迷信困扰": {
      "koan": "k028",
      "concept": "罪业心造",
      "at": "2026-06-21T15:40:49Z",
      "q_count": 20
    },
    "辨别邪说": {
      "koan": "k029",
      "concept": "信疑之力",
      "at": "2026-06-21T16:30:18Z",
      "q_count": 20
    },
    "财产纠纷": {
      "koan": "k030",
      "concept": "面具泪",
      "at": "2026-06-21T18:00:41Z",
      "q_count": 20
    },
    "对社会治安担忧": {
      "koan": "k031",
      "concept": "平价自我",
      "at": "2026-06-21T19:05:43Z",
      "q_count": 20
    },
    "临终关怀": {
      "koan": "k032",
      "concept": "临终戒疑",
      "at": "2026-06-21T20:00:15Z",
      "q_count": 19
    },
    "人际关系": {
      "koan": "k033",
      "concept": "怨",
      "at": "2026-06-21T21:00:21Z",
      "q_count": 19
    },
    "生活困境": {
      "koan": "k034",
      "concept": "机器泪",
      "at": "2026-06-21T22:10:23Z",
      "q_count": 19
    },
    "身体不适": {
      "koan": "k035",
      "concept": "念惧观",
      "at": "2026-06-21T23:20:34Z",
      "q_count": 19
    },
    "沟通障碍": {
      "koan": "k036",
      "concept": "忍结",
      "at": "2026-06-22T00:10:30Z",
      "q_count": 19
    },
    "了解佛教历史": {
      "koan": "k037",
      "concept": "信史之隙",
      "at": "2026-06-22T01:00:33Z",
      "q_count": 19
    },
    "健康饮食": {
      "koan": "k038",
      "concept": "爱畏",
      "at": "2026-06-22T02:00:31Z",
      "q_count": 19
    },
    "弘法困境": {
      "koan": "k039",
      "concept": "法义我",
      "at": "2026-06-22T03:00:30Z",
      "q_count": 19
    },
    "经济压力": {
      "koan": "k040",
      "concept": "努力之执",
      "at": "2026-06-22T03:40:38Z",
      "q_count": 19
    },
    "夫妻关系": {
      "koan": "k041",
      "concept": "情债",
      "at": "2026-06-22T04:10:18Z",
      "q_count": 19
    },
    "辨别真伪": {
      "koan": "k042",
      "concept": "疑愧交煎",
      "at": "2026-06-22T05:20:26Z",
      "q_count": 19
    },
    "团队管理": {
      "koan": "k043",
      "concept": "悔口",
      "at": "2026-06-22T06:20:27Z",
      "q_count": 19
    },
    "贫富差距": {
      "koan": "k044",
      "concept": "愧执",
      "at": "2026-06-22T07:20:50Z",
      "q_count": 19
    },
    "逃避现实": {
      "koan": "k045",
      "concept": "惧碎",
      "at": "2026-06-22T08:10:25Z",
      "q_count": 19
    },
    "信息过载": {
      "koan": "k046",
      "concept": "孤独呼救",
      "at": "2026-06-22T10:10:27Z",
      "q_count": 19
    },
    "父母养老问题": {
      "koan": "k047",
      "concept": "愧执",
      "at": "2026-06-22T10:50:46Z",
      "q_count": 19
    },
    "职业焦虑": {
      "koan": "k009",
      "concept": "(折叠近义)",
      "at": "2026-06-22T11:40:07Z",
      "q_count": 19
    },
    "修行懈怠": {
      "koan": "k048",
      "concept": "念惧观",
      "at": "2026-06-22T11:40:32Z",
      "q_count": 18
    },
    "情绪不安": {
      "koan": "k049",
      "concept": "执梦",
      "at": "2026-06-22T12:20:39Z",
      "q_count": 18
    },
    "修行障碍": {
      "koan": "k050",
      "concept": "畏忏",
      "at": "2026-06-22T13:01:03Z",
      "q_count": 18
    },
    "家庭矛盾": {
      "koan": "k051",
      "concept": "离悔",
      "at": "2026-06-22T13:50:35Z",
      "q_count": 18
    },
    "修行方法选择": {
      "koan": "k052",
      "concept": "疗信之隙",
      "at": "2026-06-22T14:40:28Z",
      "q_count": 18
    },
    "道德困境": {
      "koan": "k053",
      "concept": "护他畏己",
      "at": "2026-06-22T15:30:24Z",
      "q_count": 18
    },
    "工作压力": {
      "koan": "k010",
      "concept": "(折叠近义)",
      "at": "2026-06-22T16:30:06Z",
      "q_count": 18
    },
    "时间管理": {
      "koan": "k054",
      "concept": "过不去",
      "at": "2026-06-22T16:31:12Z",
      "q_count": 18
    },
    "辨别正邪": {
      "koan": "k055",
      "concept": "度人反障",
      "at": "2026-06-22T17:30:21Z",
      "q_count": 18
    },
    "事业发展": {
      "koan": "k056",
      "concept": "愧执",
      "at": "2026-06-22T18:45:34Z",
      "q_count": 18
    },
    "家庭和睦": {
      "koan": "k057",
      "concept": "瞒债愧结",
      "at": "2026-06-22T19:30:33Z",
      "q_count": 18
    },
    "身体健康": {
      "koan": "k058",
      "concept": "念惧观",
      "at": "2026-06-22T20:45:25Z",
      "q_count": 18
    },
    "子女教育": {
      "koan": "k059",
      "concept": "教中之愧",
      "at": "2026-06-22T22:15:18Z",
      "q_count": 18
    },
    "家庭责任": {
      "koan": "k060",
      "concept": "形式障",
      "at": "2026-06-23T00:00:35Z",
      "q_count": 18
    },
    "面对不公": {
      "koan": "k061",
      "concept": "价值废墟",
      "at": "2026-06-23T01:45:31Z",
      "q_count": 18
    },
    "对身体的执着": {
      "koan": "k062",
      "concept": "对治反噬",
      "at": "2026-06-23T03:00:52Z",
      "q_count": 18
    },
    "被误解": {
      "koan": "k063",
      "concept": "合规之对",
      "at": "2026-06-23T04:45:19Z",
      "q_count": 18
    },
    "追求神通": {
      "koan": "k064",
      "concept": "求通之痛",
      "at": "2026-06-23T06:15:39Z",
      "q_count": 18
    },
    "自我欺骗": {
      "koan": "k065",
      "concept": "愧遁",
      "at": "2026-06-23T08:15:30Z",
      "q_count": 18
    },
    "身体虚弱": {
      "koan": "k066",
      "concept": "铃寂",
      "at": "2026-06-23T09:31:12Z",
      "q_count": 18
    },
    "健康管理": {
      "koan": "k067",
      "concept": "对治反噬",
      "at": "2026-06-23T10:45:46Z",
      "q_count": 18
    },
    "自我膨胀": {
      "koan": "k068",
      "concept": "我慢",
      "at": "2026-06-23T12:00:42Z",
      "q_count": 18
    },
    "领导力": {
      "koan": "k069",
      "concept": "对境迷义",
      "at": "2026-06-23T13:30:46Z",
      "q_count": 18
    },
    "文化传承": {
      "koan": "k070",
      "concept": "搅局畏",
      "at": "2026-06-23T14:30:54Z",
      "q_count": 18
    },
    "面对批评": {
      "koan": "k071",
      "concept": "撕裂之慈",
      "at": "2026-06-23T16:02:30Z",
      "q_count": 18
    },
    "社会动荡": {
      "koan": "k072",
      "concept": "护生无力",
      "at": "2026-06-23T17:15:38Z",
      "q_count": 18
    },
    "生命危险": {
      "koan": "k073",
      "concept": "惧碎",
      "at": "2026-06-23T18:30:27Z",
      "q_count": 18
    },
    "寺院管理": {
      "koan": "k074",
      "concept": "愧护",
      "at": "2026-06-23T19:45:32Z",
      "q_count": 18
    },
    "破除迷信": {
      "koan": "k075",
      "concept": "疑畏交缠",
      "at": "2026-06-23T21:15:23Z",
      "q_count": 18
    },
    "食品安全担忧": {
      "koan": "k076",
      "concept": "价值废墟",
      "at": "2026-06-23T22:30:22Z",
      "q_count": 18
    },
    "面对诽谤": {
      "koan": "k077",
      "concept": "护疼难忍",
      "at": "2026-06-24T00:00:28Z",
      "q_count": 18
    },
    "对开悟的误解": {
      "koan": "k078",
      "concept": "对治反噬",
      "at": "2026-06-24T02:45:35Z",
      "q_count": 18
    },
    "面对质疑": {
      "koan": "k079",
      "concept": "戒惧交煎",
      "at": "2026-06-24T04:15:48Z",
      "q_count": 18
    },
    "物价上涨": {
      "koan": "k080",
      "concept": "知足之底",
      "at": "2026-06-24T05:30:47Z",
      "q_count": 18
    }
  },
  "total_types": 1982
}